{"nodes": [{"id": "app_backend_api_v1_endpoints_homologacao_py", "label": "homologacao.py", "file_type": "code", "source_file": "app\\backend\\api\\v1\\endpoints\\homologacao.py", "source_location": "L1"}, {"id": "homologacao_listar_pendentes", "label": "listar_pendentes()", "file_type": "code", "source_file": "app\\backend\\api\\v1\\endpoints\\homologacao.py", "source_location": "L28"}, {"id": "homologacao_aprovar_item", "label": "aprovar_item()", "file_type": "code", "source_file": "app\\backend\\api\\v1\\endpoints\\homologacao.py", "source_location": "L45"}, {"id": "homologacao_criar_item_proprio", "label": "criar_item_proprio()", "file_type": "code", "source_file": "app\\backend\\api\\v1\\endpoints\\homologacao.py", "source_location": "L61"}], "edges": [{"source": "app_backend_api_v1_endpoints_homologacao_py", "target": "uuid", "relation": "imports_from", "confidence": "EXTRACTED", "source_file": "app\\backend\\api\\v1\\endpoints\\homologacao.py", "source_location": "L1", "weight": 1.0}, {"source": "app_backend_api_v1_endpoints_homologacao_py", "target": "fastapi", "relation": "imports_from", "confidence": "EXTRACTED", "source_file": "app\\backend\\api\\v1\\endpoints\\homologacao.py", "source_location": "L3", "weight": 1.0}, {"source": "app_backend_api_v1_endpoints_homologacao_py", "target": "sqlalchemy_ext_asyncio", "relation": "imports_from", "confidence": "EXTRACTED", "source_file": "app\\backend\\api\\v1\\endpoints\\homologacao.py", "source_location": "L4", "weight": 1.0}, {"source": "app_backend_api_v1_endpoints_homologacao_py", "target": "backend_core_dependencies", "relation": "imports_from", "confidence": "EXTRACTED", "source_file": "app\\backend\\api\\v1\\endpoints\\homologacao.py", "source_location": "L6", "weight": 1.0}, {"source": "app_backend_api_v1_endpoints_homologacao_py", "target": "backend_schemas_common", "relation": "imports_from", "confidence": "EXTRACTED", "source_file": "app\\backend\\api\\v1\\endpoints\\homologacao.py", "source_location": "L12", "weight": 1.0}, {"source": "app_backend_api_v1_endpoints_homologacao_py", "target": "backend_schemas_homologacao", "relation": "imports_from", "confidence": "EXTRACTED", "source_file": "app\\backend\\api\\v1\\endpoints\\homologacao.py", "source_location": "L13", "weight": 1.0}, {"source": "app_backend_api_v1_endpoints_homologacao_py", "target": "backend_schemas_servico", "relation": "imports_from", "confidence": "EXTRACTED", "source_file": "app\\backend\\api\\v1\\endpoints\\homologacao.py", "source_location": "L19", "weight": 1.0}, {"source": "app_backend_api_v1_endpoints_homologacao_py", "target": "backend_services_homologacao_service", "relation": "imports_from", "confidence": "EXTRACTED", "source_file": "app\\backend\\api\\v1\\endpoints\\homologacao.py", "source_location": "L20", "weight": 1.0}, {"source": "app_backend_api_v1_endpoints_homologacao_py", "target": "homologacao_listar_pendentes", "relation": "contains", "confidence": "EXTRACTED", "source_file": "app\\backend\\api\\v1\\endpoints\\homologacao.py", "source_location": "L28", "weight": 1.0}, {"source": "app_backend_api_v1_endpoints_homologacao_py", "target": "homologacao_aprovar_item", "relation": "contains", "confidence": "EXTRACTED", "source_file": "app\\backend\\api\\v1\\endpoints\\homologacao.py", "source_location": "L45", "weight": 1.0}, {"source": "app_backend_api_v1_endpoints_homologacao_py", "target": "homologacao_criar_item_proprio", "relation": "contains", "confidence": "EXTRACTED", "source_file": "app\\backend\\api\\v1\\endpoints\\homologacao.py", "source_location": "L61", "weight": 1.0}], "raw_calls": [{"caller_nid": "homologacao_listar_pendentes", "callee": "require_cliente_perfil", "source_file": "app\\backend\\api\\v1\\endpoints\\homologacao.py", "source_location": "L35"}, {"caller_nid": "homologacao_aprovar_item", "callee": "require_cliente_perfil", "source_file": "app\\backend\\api\\v1\\endpoints\\homologacao.py", "source_location": "L51"}, {"caller_nid": "homologacao_aprovar_item", "callee": "aprovar", "source_file": "app\\backend\\api\\v1\\endpoints\\homologacao.py", "source_location": "L52"}, {"caller_nid": "homologacao_criar_item_proprio", "callee": "require_cliente_access", "source_file": "app\\backend\\api\\v1\\endpoints\\homologacao.py", "source_location": "L66"}, {"caller_nid": "homologacao_criar_item_proprio", "callee": "model_validate", "source_file": "app\\backend\\api\\v1\\endpoints\\homologacao.py", "source_location": "L72"}]}