{"nodes": [{"id": "app_backend_models_proposta_py", "label": "proposta.py", "file_type": "code", "source_file": "app\\backend\\models\\proposta.py", "source_location": "L1"}, {"id": "proposta_proposta", "label": "Proposta", "file_type": "code", "source_file": "app\\backend\\models\\proposta.py", "source_location": "L14"}, {"id": "base", "label": "Base", "file_type": "code", "source_file": "", "source_location": ""}, {"id": "timestampmixin", "label": "TimestampMixin", "file_type": "code", "source_file": "", "source_location": ""}, {"id": "proposta_pqimportacao", "label": "PqImportacao", "file_type": "code", "source_file": "app\\backend\\models\\proposta.py", "source_location": "L69"}, {"id": "proposta_pqitem", "label": "PqItem", "file_type": "code", "source_file": "app\\backend\\models\\proposta.py", "source_location": "L95"}, {"id": "proposta_propostaitem", "label": "PropostaItem", "file_type": "code", "source_file": "app\\backend\\models\\proposta.py", "source_location": "L135"}, {"id": "proposta_propostaitemcomposicao", "label": "PropostaItemComposicao", "file_type": "code", "source_file": "app\\backend\\models\\proposta.py", "source_location": "L181"}], "edges": [{"source": "app_backend_models_proposta_py", "target": "uuid", "relation": "imports", "confidence": "EXTRACTED", "source_file": "app\\backend\\models\\proposta.py", "source_location": "L1", "weight": 1.0}, {"source": "app_backend_models_proposta_py", "target": "datetime", "relation": "imports_from", "confidence": "EXTRACTED", "source_file": "app\\backend\\models\\proposta.py", "source_location": "L2", "weight": 1.0}, {"source": "app_backend_models_proposta_py", "target": "decimal", "relation": "imports_from", "confidence": "EXTRACTED", "source_file": "app\\backend\\models\\proposta.py", "source_location": "L3", "weight": 1.0}, {"source": "app_backend_models_proposta_py", "target": "uuid", "relation": "imports_from", "confidence": "EXTRACTED", "source_file": "app\\backend\\models\\proposta.py", "source_location": "L4", "weight": 1.0}, {"source": "app_backend_models_proposta_py", "target": "sqlalchemy", "relation": "imports_from", "confidence": "EXTRACTED", "source_file": "app\\backend\\models\\proposta.py", "source_location": "L6", "weight": 1.0}, {"source": "app_backend_models_proposta_py", "target": "sqlalchemy_dialects_postgresql", "relation": "imports_from", "confidence": "EXTRACTED", "source_file": "app\\backend\\models\\proposta.py", "source_location": "L7", "weight": 1.0}, {"source": "app_backend_models_proposta_py", "target": "sqlalchemy_orm", "relation": "imports_from", "confidence": "EXTRACTED", "source_file": "app\\backend\\models\\proposta.py", "source_location": "L8", "weight": 1.0}, {"source": "app_backend_models_proposta_py", "target": "backend_models_base", "relation": "imports_from", "confidence": "EXTRACTED", "source_file": "app\\backend\\models\\proposta.py", "source_location": "L10", "weight": 1.0}, {"source": "app_backend_models_proposta_py", "target": "backend_models_enums", "relation": "imports_from", "confidence": "EXTRACTED", "source_file": "app\\backend\\models\\proposta.py", "source_location": "L11", "weight": 1.0}, {"source": "app_backend_models_proposta_py", "target": "proposta_proposta", "relation": "contains", "confidence": "EXTRACTED", "source_file": "app\\backend\\models\\proposta.py", "source_location": "L14", "weight": 1.0}, {"source": "proposta_proposta", "target": "base", "relation": "inherits", "confidence": "EXTRACTED", "source_file": "app\\backend\\models\\proposta.py", "source_location": "L14", "weight": 1.0}, {"source": "proposta_proposta", "target": "timestampmixin", "relation": "inherits", "confidence": "EXTRACTED", "source_file": "app\\backend\\models\\proposta.py", "source_location": "L14", "weight": 1.0}, {"source": "app_backend_models_proposta_py", "target": "proposta_pqimportacao", "relation": "contains", "confidence": "EXTRACTED", "source_file": "app\\backend\\models\\proposta.py", "source_location": "L69", "weight": 1.0}, {"source": "proposta_pqimportacao", "target": "base", "relation": "inherits", "confidence": "EXTRACTED", "source_file": "app\\backend\\models\\proposta.py", "source_location": "L69", "weight": 1.0}, {"source": "proposta_pqimportacao", "target": "timestampmixin", "relation": "inherits", "confidence": "EXTRACTED", "source_file": "app\\backend\\models\\proposta.py", "source_location": "L69", "weight": 1.0}, {"source": "app_backend_models_proposta_py", "target": "proposta_pqitem", "relation": "contains", "confidence": "EXTRACTED", "source_file": "app\\backend\\models\\proposta.py", "source_location": "L95", "weight": 1.0}, {"source": "proposta_pqitem", "target": "base", "relation": "inherits", "confidence": "EXTRACTED", "source_file": "app\\backend\\models\\proposta.py", "source_location": "L95", "weight": 1.0}, {"source": "proposta_pqitem", "target": "timestampmixin", "relation": "inherits", "confidence": "EXTRACTED", "source_file": "app\\backend\\models\\proposta.py", "source_location": "L95", "weight": 1.0}, {"source": "app_backend_models_proposta_py", "target": "proposta_propostaitem", "relation": "contains", "confidence": "EXTRACTED", "source_file": "app\\backend\\models\\proposta.py", "source_location": "L135", "weight": 1.0}, {"source": "proposta_propostaitem", "target": "base", "relation": "inherits", "confidence": "EXTRACTED", "source_file": "app\\backend\\models\\proposta.py", "source_location": "L135", "weight": 1.0}, {"source": "proposta_propostaitem", "target": "timestampmixin", "relation": "inherits", "confidence": "EXTRACTED", "source_file": "app\\backend\\models\\proposta.py", "source_location": "L135", "weight": 1.0}, {"source": "app_backend_models_proposta_py", "target": "proposta_propostaitemcomposicao", "relation": "contains", "confidence": "EXTRACTED", "source_file": "app\\backend\\models\\proposta.py", "source_location": "L181", "weight": 1.0}, {"source": "proposta_propostaitemcomposicao", "target": "base", "relation": "inherits", "confidence": "EXTRACTED", "source_file": "app\\backend\\models\\proposta.py", "source_location": "L181", "weight": 1.0}], "raw_calls": []}